Metadata-Version: 1.1
Name: nixdeps
Version: 0.0.1
Summary: A setuptools entrypoint to store dependencies on Nix packages at build-time
Home-page: https://github.com/catern/rsyscall
Author: catern
Author-email: sbaugh@catern.com
License: MIT
Platform: UNKNOWN
Classifier: Programming Language :: Python :: 3
Classifier: License :: OSI Approved :: MIT License
